[
    { "word": "ZABT", "definition": "1. Sıkı tutma. 2. İdaresi altına alma, kendine mal etme. 3. Silah zoru ile bir yeri alma. 4. Anlama, kavrama. 5. Kaydetme, özetini yazma." },
    { "word": "ZÂHİB", "definition": "1. Gidici, giden. 2. Bir fikre veya zanna uyan, kapılan." },
    { "word": "ZÂHİR", "definition": "Açık, belli, görünür, meydanda olan." },
    { "word": "ZÂHİRÎ", "definition": "Dıştan görünen, meydanda olan." },
    { "word": "ZAİL", "definition": "Sona eren, sürekli olmayan." },
    { "word": "ZAMİR", "definition": "1. Her şeyin iç yüzü. 2. Yürek, vicdan. 3. Gizli fikir. 4. Zamir, ismin yerini tutan kelime." },
    { "word": "ZÂNİ", "definition": "Zina eden erkek." },
    { "word": "ZÂNİYE", "definition": "Zina eden kadın." },
    { "word": "ZARAR", "definition": "Ziyan, eksiklik, kayıp." },
    { "word": "ZARF", "definition": "Yer ve zaman bildiren edat." },
    { "word": "ZAT", "definition": "Kendi, asıl, öz, cevher, saygıdeğer kişi." },
    { "word": "ZAYİ'", "definition": "Elden çıkan, yitik, kaybolan." },
    { "word": "ZAYİAT", "definition": "Kayıplar, yitikler." },
    { "word": "ZEBÂNÎ", "definition": "Zebanî, cehennemlikleri cehenneme atan melek." },
    { "word": "ZEBERCED", "definition": "Zümrütten daha açık renkte bir süs taşı." },
    { "word": "ZEBH", "definition": "Boğazlama, kesme, kurban kesme." },
    { "word": "ZECR", "definition": "1. Yasaklama, yaptırmama. 2. Zorlama, zorla yaptırma, angarya işletme sıkma, eziyet." },
    { "word": "ZEKER", "definition": "Erkek, erkeklik organı." },
    { "word": "ZELİL", "definition": "Hor, hakir, alçak." },
    { "word": "ZELLE", "definition": "1. Ayak sürçüp kayma. 2. Hata, suç." },
    { "word": "ZEM (ZEMM)", "definition": "Birinin kötülüğünü söyleme, ayıplama, yerme, çekiştirme." },
    { "word": "ZEMHERİR", "definition": "Karakış." },
    { "word": "ZEMZEME", "definition": "1. Ezgili ses, terennüm, teganni. 2. Mezamir'i okuyanların teranesi (Zebur)." },
    { "word": "ZENB", "definition": "Günah, suç, kabahat." },
    { "word": "ZEVAL", "definition": "1. Zail olma, sona erme. 2. Aşağılama, inme. 3. Güneşin başucunda, tam tepeden bulunma zamanı zeval vakti, öğle vakti." },
    { "word": "ZEVC", "definition": "Çift, eş." },
    { "word": "ZEVCYEN", "definition": "Karı-koca, iki eş." },
    { "word": "ZEVİ'L-UKUL", "definition": "Akıl sahipleri, akıllılar." },
    { "word": "ZİKR", "definition": "1. Zikir, anma, hatıra getirme. 2. Ağıza alma, adını söyleme. 3. Anlatma, ifade etme. 4. Övme, iyilikle anma. 5. Tasavvufi anlamıyla Allah adını anarak zikretme." },
    { "word": "ZİKR-İ CEMİL", "definition": "Güzel zikir, övgü." },
    { "word": "ZİKRULLAH", "definition": "Allah'ı anma." },
    { "word": "ZİLLET", "definition": "Alçaklık, aşağılık." },
    { "word": "ZİMMÎ", "definition": "1. İslâm devletinde yaşayan gayr-i müslim. 2. Haraç veren, raiyye." },
    { "word": "ZİNET", "definition": "Süs eşyası, bezek." },
    { "word": "ZİRA'", "definition": "Dirsekten orta parmak ucuna kadar olan uzunluk ölçüsü, 75-90 santim arasında değişir." },
    { "word": "ZÎRAHİM-İ MAHREM", "definition": "Nikah düşmeyen akraba kadın." },
    { "word": "ZİŞAN", "definition": "Şanlı, ünlü, gösterişli." },
    { "word": "ZİYA", "definition": "Işık, aydınlık." },
    { "word": "ZUHR", "definition": "Öğle zamanı, öğle namazı." },
    { "word": "ZULM", "definition": "Zulüm, haksızlık, eziyet." },
    { "word": "ZULMET", "definition": "Karanlık." },
    { "word": "ZÜBDE", "definition": "Bir şeyin en seçkin parçası, öz, özet." },
    { "word": "ZÜBUR-ZÜBÜR", "definition": "Kitaplar, yazılı şeyler." },
    { "word": "ZÜHD", "definition": "Dünya lezzetlerinden el çekerek ibadetle meşgul olma, sofuluk." },
    { "word": "ZÜHÛL", "definition": "İsteyerek veya elde olmayarak unutma, geçiştirme, yanılma." },
    { "word": "ZÜLCELAL", "definition": "Celal sahibi, Allah." },
    { "word": "ZÜLKARNEYN", "definition": "İki boynuz sahibi, Kur'ân-ı Kerim'de adı geçen bir hükümdar, iki yönlü." },
    { "word": "ZÜLL", "definition": "Horluk, hakirlik, alçaklık." },
    { "word": "ZÜRRİYET", "definition": "Soy, nesil, kuşak." }
]